{
  "project_info": {
    "project_number": "707138239166",
    "project_id": "echospartan-2a2dd",
    "storage_bucket": "echospartan-2a2dd.firebasestorage.app"
  },
  "client": [
    {
      "client_info": {
        "mobilesdk_app_id": "1:707138239166:android:a32eb742388be8b7467cef",
        "android_client_info": {
          "package_name": "com.example.try_1"
        }
      },
      "oauth_client": [],
      "api_key": [
        {
          "current_key": "AIzaSyA2rEMdDd5xS5JX6uauNZuiqbBwqKyyGJs"
        }
      ],
      "services": {
        "appinvite_service": {
          "other_platform_oauth_client": []
        }
      }
    }
  ],
  "configuration_version": "1"
}